google/cloud/bigquery_migration/__init__.py
google/cloud/bigquery_migration/gapic_version.py
google/cloud/bigquery_migration/py.typed
google/cloud/bigquery_migration_v2/__init__.py
google/cloud/bigquery_migration_v2/gapic_metadata.json
google/cloud/bigquery_migration_v2/gapic_version.py
google/cloud/bigquery_migration_v2/py.typed
google/cloud/bigquery_migration_v2/services/__init__.py
google/cloud/bigquery_migration_v2/services/migration_service/__init__.py
google/cloud/bigquery_migration_v2/services/migration_service/async_client.py
google/cloud/bigquery_migration_v2/services/migration_service/client.py
google/cloud/bigquery_migration_v2/services/migration_service/pagers.py
google/cloud/bigquery_migration_v2/services/migration_service/transports/__init__.py
google/cloud/bigquery_migration_v2/services/migration_service/transports/base.py
google/cloud/bigquery_migration_v2/services/migration_service/transports/grpc.py
google/cloud/bigquery_migration_v2/services/migration_service/transports/grpc_asyncio.py
google/cloud/bigquery_migration_v2/types/__init__.py
google/cloud/bigquery_migration_v2/types/migration_entities.py
google/cloud/bigquery_migration_v2/types/migration_error_details.py
google/cloud/bigquery_migration_v2/types/migration_metrics.py
google/cloud/bigquery_migration_v2/types/migration_service.py
google/cloud/bigquery_migration_v2/types/translation_config.py
google/cloud/bigquery_migration_v2/types/translation_details.py
google/cloud/bigquery_migration_v2/types/translation_suggestion.py
google/cloud/bigquery_migration_v2/types/translation_usability.py
google/cloud/bigquery_migration_v2alpha/__init__.py
google/cloud/bigquery_migration_v2alpha/gapic_metadata.json
google/cloud/bigquery_migration_v2alpha/gapic_version.py
google/cloud/bigquery_migration_v2alpha/py.typed
google/cloud/bigquery_migration_v2alpha/services/__init__.py
google/cloud/bigquery_migration_v2alpha/services/migration_service/__init__.py
google_cloud_bigquery_migration-0.13.0.dist-info/licenses/LICENSE
google_cloud_bigquery_migration-0.13.0.dist-info/METADATA
google_cloud_bigquery_migration-0.13.0.dist-info/WHEEL
google_cloud_bigquery_migration-0.13.0.dist-info/top_level.txt
google_cloud_bigquery_migration-0.13.0.dist-info/RECORD
